[
	{
		"kind": "youtube#commentThread",
		"etag": "6OThboeZspFHS4wZgld9vuZAqL4",
		"id": "UgwCmrcceqlCFwOLO0p4AaABAg",
		"snippet": {
			"channelId": "UCKIEPfI9D32EnsP6oasduSg",
			"videoId": "7kcz6q83bck",
			"topLevelComment": {
				"kind": "youtube#comment",
				"etag": "ICtPtAhQOhziX9IHn6cEudFwvKY",
				"id": "UgwCmrcceqlCFwOLO0p4AaABAg",
				"snippet": {
					"channelId": "UCKIEPfI9D32EnsP6oasduSg",
					"videoId": "7kcz6q83bck",
					"textDisplay": "พูดความในใจ ระบายกับเราได้ฟรี 💓\r<br>บนแอปพลิเคชั่นออลล์จิต Alljit (พื้นที่ปลอดภัยสำหรับคุณ)\r<br>ดาวน์โหลดของ iOS\r<br><a href=\"https://apps.apple.com/th/app/alljit/id1549529345?l=th\">https://apps.apple.com/th/app/alljit/id1549529345?l=th\r</a><br>ดาวน์โหลดของ Android\r<br><a href=\"https://play.google.com/store/apps/details?id=com.alljit\">https://play.google.com/store/apps/details?id=com.alljit</a>",
					"textOriginal": "พูดความในใจ ระบายกับเราได้ฟรี 💓\r\nบนแอปพลิเคชั่นออลล์จิต Alljit (พื้นที่ปลอดภัยสำหรับคุณ)\r\nดาวน์โหลดของ iOS\r\nhttps://apps.apple.com/th/app/alljit/id1549529345?l=th\r\nดาวน์โหลดของ Android\r\nhttps://play.google.com/store/apps/details?id=com.alljit",
					"authorDisplayName": "@alljit2899",
					"authorProfileImageUrl": "https://yt3.ggpht.com/9G1VHwlixOYAKYITU2BIjS5JAlBCGPp9ynPRsZQcdigQLvSokTuhPb28QTiSf2rPzQHMReIV1yw=s48-c-k-c0x00ffffff-no-rj",
					"authorChannelUrl": "http://www.youtube.com/channel/UCKIEPfI9D32EnsP6oasduSg",
					"authorChannelId": {
						"value": "UCKIEPfI9D32EnsP6oasduSg"
					},
					"canRate": true,
					"viewerRating": "none",
					"likeCount": 0,
					"publishedAt": "2021-10-20T08:33:05Z",
					"updatedAt": "2021-10-20T08:33:05Z"
				}
			},
			"canReply": true,
			"totalReplyCount": 0,
			"isPublic": true
		}
	},
	{
		"kind": "youtube#commentThread",
		"etag": "dXw1dOZ9mTufigz3KvXw_yiiGx0",
		"id": "UgwPthR8SM1hwSkP9RZ4AaABAg",
		"snippet": {
			"channelId": "UCKIEPfI9D32EnsP6oasduSg",
			"videoId": "7kcz6q83bck",
			"topLevelComment": {
				"kind": "youtube#comment",
				"etag": "a_i0OhkLwXBKYl3ry-3UZEKtnSs",
				"id": "UgwPthR8SM1hwSkP9RZ4AaABAg",
				"snippet": {
					"channelId": "UCKIEPfI9D32EnsP6oasduSg",
					"videoId": "7kcz6q83bck",
					"textDisplay": "ส่วนใหญ่ในคอมเม้นเจอแต่คนโดนกระทำ ผมนี่เป็นฝ่ายกระทำแล้วก็มารู้สึกไม่ดี คิดว่าตัวเองไม่ดีตลอดเวลา โง่เหลือเกิน คนอื่นก็ไม่ได้ดี ที่คนอื่นได้ดีเพราะมีเพื่อน ค่าความโชคดีเขามีมากกว่า คิดแบบนี้จนมีผลกับสุขภาพจิตจนคิดว่าตัวเองเป็นอะไร ผมก็ได้เข้าใจว่าไม่ได้พูดมันออกมา จนกลายเป็นเงียบ เงียบจนคนอื่นรู้สึกไม่ดี วัน ๆ ไม่พูดอะไรเลย จนเขาไล่ออกจากที่ทำงานก็มี แต่ถามกลับไป ก็ไม่มีความรู้สึกอะไรเลยที่จะพูด ชวนคุยมนุษย์นี่มันเป็นยังไงกันนะถามตัวเอง ไม่ยอมรับในสิ่งที่มีอยู่ตรงหน้า หลัก ๆ คงเป็นเรื่องไม่รักตัวเองนั่นแหละ เพราะไม่ยอมรับตัวเองเลยมองโลกในแง่ลบ จะคิดดีเหมือนสมัยก่อนก็ทำไม่ได้ นี่เราเก่งขึ้นบ้างรึเปล่า กำลังเป็นภาระของคนอื่นรึเปล่า สุดท้ายผมทำอะไรได้บ้าง คำถามพวกนี้มันวนอยู่ในหัวผมมา 5 ปี มีแต่เรื่องที่หาทางออกไม่ได้ ผมพูดตรง ๆ ก็สงสารแม่ ไม่อยากให้แม่คิดลบไปด้วย ผมมันน่าเบื่อแบบนี้ก็ไม่มีใครเลยไม่ต้องรู้จักใครเลยซะจะดีกว่า (นี่คือความคิดผม พูดยาวซะเหลือเกิน)",
					"textOriginal": "ส่วนใหญ่ในคอมเม้นเจอแต่คนโดนกระทำ ผมนี่เป็นฝ่ายกระทำแล้วก็มารู้สึกไม่ดี คิดว่าตัวเองไม่ดีตลอดเวลา โง่เหลือเกิน คนอื่นก็ไม่ได้ดี ที่คนอื่นได้ดีเพราะมีเพื่อน ค่าความโชคดีเขามีมากกว่า คิดแบบนี้จนมีผลกับสุขภาพจิตจนคิดว่าตัวเองเป็นอะไร ผมก็ได้เข้าใจว่าไม่ได้พูดมันออกมา จนกลายเป็นเงียบ เงียบจนคนอื่นรู้สึกไม่ดี วัน ๆ ไม่พูดอะไรเลย จนเขาไล่ออกจากที่ทำงานก็มี แต่ถามกลับไป ก็ไม่มีความรู้สึกอะไรเลยที่จะพูด ชวนคุยมนุษย์นี่มันเป็นยังไงกันนะถามตัวเอง ไม่ยอมรับในสิ่งที่มีอยู่ตรงหน้า หลัก ๆ คงเป็นเรื่องไม่รักตัวเองนั่นแหละ เพราะไม่ยอมรับตัวเองเลยมองโลกในแง่ลบ จะคิดดีเหมือนสมัยก่อนก็ทำไม่ได้ นี่เราเก่งขึ้นบ้างรึเปล่า กำลังเป็นภาระของคนอื่นรึเปล่า สุดท้ายผมทำอะไรได้บ้าง คำถามพวกนี้มันวนอยู่ในหัวผมมา 5 ปี มีแต่เรื่องที่หาทางออกไม่ได้ ผมพูดตรง ๆ ก็สงสารแม่ ไม่อยากให้แม่คิดลบไปด้วย ผมมันน่าเบื่อแบบนี้ก็ไม่มีใครเลยไม่ต้องรู้จักใครเลยซะจะดีกว่า (นี่คือความคิดผม พูดยาวซะเหลือเกิน)",
					"authorDisplayName": "@KitsuneArm",
					"authorProfileImageUrl": "https://yt3.ggpht.com/FYvvprvt2kr460xYcu-Ph1W_VzN3QvzWQHGMPEIlLnvpdRUHqMm_FyN1Ymt4P0S2DbyxoiK3EQ=s48-c-k-c0x00ffffff-no-rj",
					"authorChannelUrl": "http://www.youtube.com/channel/UCCjrzrWX6XxLRDnOVsH52UQ",
					"authorChannelId": {
						"value": "UCCjrzrWX6XxLRDnOVsH52UQ"
					},
					"canRate": true,
					"viewerRating": "none",
					"likeCount": 0,
					"publishedAt": "2023-05-18T20:19:51Z",
					"updatedAt": "2023-05-18T20:19:51Z"
				}
			},
			"canReply": true,
			"totalReplyCount": 1,
			"isPublic": true
		},
		"replies": {
			"comments": [
				{
					"kind": "youtube#comment",
					"etag": "wEWKPIK_H7s5QHpGoEgLfrPqp0g",
					"id": "UgwPthR8SM1hwSkP9RZ4AaABAg.9prxho2MDj29pu42lwiqgv",
					"snippet": {
						"channelId": "UCKIEPfI9D32EnsP6oasduSg",
						"videoId": "7kcz6q83bck",
						"textDisplay": "แอดเป็นกำลังใจให้น้ามีเรื่องอะไรไม่สบายใจมาระบายที่แอป Alljit ได้นะคะ💙",
						"textOriginal": "แอดเป็นกำลังใจให้น้ามีเรื่องอะไรไม่สบายใจมาระบายที่แอป Alljit ได้นะคะ💙",
						"parentId": "UgwPthR8SM1hwSkP9RZ4AaABAg",
						"authorDisplayName": "@alljit2899",
						"authorProfileImageUrl": "https://yt3.ggpht.com/9G1VHwlixOYAKYITU2BIjS5JAlBCGPp9ynPRsZQcdigQLvSokTuhPb28QTiSf2rPzQHMReIV1yw=s48-c-k-c0x00ffffff-no-rj",
						"authorChannelUrl": "http://www.youtube.com/channel/UCKIEPfI9D32EnsP6oasduSg",
						"authorChannelId": {
							"value": "UCKIEPfI9D32EnsP6oasduSg"
						},
						"canRate": true,
						"viewerRating": "none",
						"likeCount": 1,
						"publishedAt": "2023-05-19T16:02:29Z",
						"updatedAt": "2023-05-19T16:02:29Z"
					}
				}
			]
		}
	},
	{
		"kind": "youtube#commentThread",
		"etag": "irhdjpeN5SGPtrFxD2rOqtY90fs",
		"id": "Ugz8DoPUULXNP7miEYx4AaABAg",
		"snippet": {
			"channelId": "UCKIEPfI9D32EnsP6oasduSg",
			"videoId": "7kcz6q83bck",
			"topLevelComment": {
				"kind": "youtube#comment",
				"etag": "HLrI5WbLnWxCk5DmxozWnrlwjtk",
				"id": "Ugz8DoPUULXNP7miEYx4AaABAg",
				"snippet": {
					"channelId": "UCKIEPfI9D32EnsP6oasduSg",
					"videoId": "7kcz6q83bck",
					"textDisplay": "จะบวกกับคนที่มีศิล.สมาธิ.ปัญญาเท่านั้น.แล้วคนไม่มีศิล.สมา.ปัญญามันเช้ากันไม่ได้ดอกตรงกันข้ามเราจะมีแต่ความเดึอดเนึ้อร้อนใจด้วยเท่านั้น.หรึอเข้ากันไม่ได้",
					"textOriginal": "จะบวกกับคนที่มีศิล.สมาธิ.ปัญญาเท่านั้น.แล้วคนไม่มีศิล.สมา.ปัญญามันเช้ากันไม่ได้ดอกตรงกันข้ามเราจะมีแต่ความเดึอดเนึ้อร้อนใจด้วยเท่านั้น.หรึอเข้ากันไม่ได้",
					"authorDisplayName": "@tckhvjtf6542",
					"authorProfileImageUrl": "https://yt3.ggpht.com/ytc/AIf8zZQKdoG2cTZT0KAJiqeFEoPJmvMpbrKT3DjiEp68_F7GRoafHn4-ZkTtWq1eckg6=s48-c-k-c0x00ffffff-no-rj",
					"authorChannelUrl": "http://www.youtube.com/channel/UC9arjuC6vW-lOxSOPiuIt6A",
					"authorChannelId": {
						"value": "UC9arjuC6vW-lOxSOPiuIt6A"
					},
					"canRate": true,
					"viewerRating": "none",
					"likeCount": 1,
					"publishedAt": "2021-11-19T14:08:31Z",
					"updatedAt": "2021-11-19T14:08:31Z"
				}
			},
			"canReply": true,
			"totalReplyCount": 0,
			"isPublic": true
		}
	},
	{
		"kind": "youtube#commentThread",
		"etag": "t5axtawQpbxtDSCyGUl2pA83Ldo",
		"id": "UgyesQgKbTKSZUI1Sc54AaABAg",
		"snippet": {
			"channelId": "UCKIEPfI9D32EnsP6oasduSg",
			"videoId": "7kcz6q83bck",
			"topLevelComment": {
				"kind": "youtube#comment",
				"etag": "_oieQ2qQuBWDoLlBEjc2y1xM6J8",
				"id": "UgyesQgKbTKSZUI1Sc54AaABAg",
				"snippet": {
					"channelId": "UCKIEPfI9D32EnsP6oasduSg",
					"videoId": "7kcz6q83bck",
					"textDisplay": "ฃ",
					"textOriginal": "ฃ",
					"authorDisplayName": "@user-xp3ev9cl1h",
					"authorProfileImageUrl": "https://yt3.ggpht.com/ytc/AIf8zZQlbl2x5RVBsJPM2kJDMUv6SvuoRT3RIkIMZUQdFUOCqg=s48-c-k-c0x00ffffff-no-rj",
					"authorChannelUrl": "http://www.youtube.com/channel/UCXTL8W2RzgI1znv7eNc8THA",
					"authorChannelId": {
						"value": "UCXTL8W2RzgI1znv7eNc8THA"
					},
					"canRate": true,
					"viewerRating": "none",
					"likeCount": 0,
					"publishedAt": "2021-11-13T14:17:35Z",
					"updatedAt": "2021-11-13T14:17:35Z"
				}
			},
			"canReply": true,
			"totalReplyCount": 0,
			"isPublic": true
		}
	},
	{
		"kind": "youtube#commentThread",
		"etag": "z2JMvGqmVKzI7ojH_d2hRLCzuwk",
		"id": "UgwEktwgUxyNcmc0g3R4AaABAg",
		"snippet": {
			"channelId": "UCKIEPfI9D32EnsP6oasduSg",
			"videoId": "7kcz6q83bck",
			"topLevelComment": {
				"kind": "youtube#comment",
				"etag": "9D-W8UNA_IIBrXk-y6Z-hVHnLO8",
				"id": "UgwEktwgUxyNcmc0g3R4AaABAg",
				"snippet": {
					"channelId": "UCKIEPfI9D32EnsP6oasduSg",
					"videoId": "7kcz6q83bck",
					"textDisplay": "ขอบคุณมากครับ",
					"textOriginal": "ขอบคุณมากครับ",
					"authorDisplayName": "@user-bp7gj9tw9r",
					"authorProfileImageUrl": "https://yt3.ggpht.com/ytc/AIf8zZRrGa66V46_1wx-w4KMIuSBZdEpNATgjncly-O_6A=s48-c-k-c0x00ffffff-no-rj",
					"authorChannelUrl": "http://www.youtube.com/channel/UCWCo2aIO3liqrRYTPwbdHYA",
					"authorChannelId": {
						"value": "UCWCo2aIO3liqrRYTPwbdHYA"
					},
					"canRate": true,
					"viewerRating": "none",
					"likeCount": 0,
					"publishedAt": "2021-10-23T04:02:54Z",
					"updatedAt": "2021-10-23T04:02:54Z"
				}
			},
			"canReply": true,
			"totalReplyCount": 1,
			"isPublic": true
		},
		"replies": {
			"comments": [
				{
					"kind": "youtube#comment",
					"etag": "q_PsqVSgiiWk3k28TjuBj2x-gRw",
					"id": "UgwEktwgUxyNcmc0g3R4AaABAg.9TpMD1uvea99Tv-Bsputey",
					"snippet": {
						"channelId": "UCKIEPfI9D32EnsP6oasduSg",
						"videoId": "7kcz6q83bck",
						"textDisplay": "💕",
						"textOriginal": "💕",
						"parentId": "UgwEktwgUxyNcmc0g3R4AaABAg",
						"authorDisplayName": "@alljit2899",
						"authorProfileImageUrl": "https://yt3.ggpht.com/9G1VHwlixOYAKYITU2BIjS5JAlBCGPp9ynPRsZQcdigQLvSokTuhPb28QTiSf2rPzQHMReIV1yw=s48-c-k-c0x00ffffff-no-rj",
						"authorChannelUrl": "http://www.youtube.com/channel/UCKIEPfI9D32EnsP6oasduSg",
						"authorChannelId": {
							"value": "UCKIEPfI9D32EnsP6oasduSg"
						},
						"canRate": true,
						"viewerRating": "none",
						"likeCount": 0,
						"publishedAt": "2021-10-25T08:37:13Z",
						"updatedAt": "2021-10-25T08:37:13Z"
					}
				}
			]
		}
	},
	{
		"kind": "youtube#commentThread",
		"etag": "S4WRAnDZl6Y-neddXPu_paPcruw",
		"id": "Ugwk0eopK8QTv5oFPIR4AaABAg",
		"snippet": {
			"channelId": "UCKIEPfI9D32EnsP6oasduSg",
			"videoId": "7kcz6q83bck",
			"topLevelComment": {
				"kind": "youtube#comment",
				"etag": "9A9OPDIHUNKj-Sk8UA4lyy9Qlmk",
				"id": "Ugwk0eopK8QTv5oFPIR4AaABAg",
				"snippet": {
					"channelId": "UCKIEPfI9D32EnsP6oasduSg",
					"videoId": "7kcz6q83bck",
					"textDisplay": "จริงค่ะ ช่วงนี้เจอแต่คนอื่นพูดไม่ดี กระทำไม่ดีใส่ตลอด จิตใจหดหู่ คิดร้ายคิดลบกับกลุ่มคนพวกนี้ คิดบวกให้ตัวเอง หรือคิดบวกกับคนพวกนี้ไม่ได้จริงๆค่ะ",
					"textOriginal": "จริงค่ะ ช่วงนี้เจอแต่คนอื่นพูดไม่ดี กระทำไม่ดีใส่ตลอด จิตใจหดหู่ คิดร้ายคิดลบกับกลุ่มคนพวกนี้ คิดบวกให้ตัวเอง หรือคิดบวกกับคนพวกนี้ไม่ได้จริงๆค่ะ",
					"authorDisplayName": "@pechcyn.2136",
					"authorProfileImageUrl": "https://yt3.ggpht.com/ytc/AIf8zZSsi0bd7Jdhgr27F5gAQ5911D-plSnr8enWow=s48-c-k-c0x00ffffff-no-rj",
					"authorChannelUrl": "http://www.youtube.com/channel/UCfsKplNElrG6rzC-qrRr2ow",
					"authorChannelId": {
						"value": "UCfsKplNElrG6rzC-qrRr2ow"
					},
					"canRate": true,
					"viewerRating": "none",
					"likeCount": 1,
					"publishedAt": "2021-10-22T00:09:40Z",
					"updatedAt": "2021-10-22T00:09:40Z"
				}
			},
			"canReply": true,
			"totalReplyCount": 2,
			"isPublic": true
		},
		"replies": {
			"comments": [
				{
					"kind": "youtube#comment",
					"etag": "G4OZ23FLFPbpGJAuW2iCspD1Q0o",
					"id": "Ugwk0eopK8QTv5oFPIR4AaABAg.9TmMirE421c9Tms_NFftYs",
					"snippet": {
						"channelId": "UCKIEPfI9D32EnsP6oasduSg",
						"videoId": "7kcz6q83bck",
						"textDisplay": "หากเราไม่สามารถที่จะคิดบวกได้ ก็อย่าพยายามหนีความคิดของเรา หากรู้สึกแบบไหนก็ปล่อยให้เราได้รู้สึกแบบนั้นต่อไป แต่ขอแค่เราสามารถจัดการกับความคิด ความรู้สึกนั้นของเราไม่ให้ส่งผลกระทบต่อการใช้ชีวิต หรือส่งผลกระทบต่อจิตใจเรา คิดลบกับคนพวกนั้นได้ แต่อย่าให้ความคิดลบนั้นส่งผลด้านลบให้กับตัวเราเองนะคะ💕",
						"textOriginal": "หากเราไม่สามารถที่จะคิดบวกได้ ก็อย่าพยายามหนีความคิดของเรา หากรู้สึกแบบไหนก็ปล่อยให้เราได้รู้สึกแบบนั้นต่อไป แต่ขอแค่เราสามารถจัดการกับความคิด ความรู้สึกนั้นของเราไม่ให้ส่งผลกระทบต่อการใช้ชีวิต หรือส่งผลกระทบต่อจิตใจเรา คิดลบกับคนพวกนั้นได้ แต่อย่าให้ความคิดลบนั้นส่งผลด้านลบให้กับตัวเราเองนะคะ💕",
						"parentId": "Ugwk0eopK8QTv5oFPIR4AaABAg",
						"authorDisplayName": "@alljit2899",
						"authorProfileImageUrl": "https://yt3.ggpht.com/9G1VHwlixOYAKYITU2BIjS5JAlBCGPp9ynPRsZQcdigQLvSokTuhPb28QTiSf2rPzQHMReIV1yw=s48-c-k-c0x00ffffff-no-rj",
						"authorChannelUrl": "http://www.youtube.com/channel/UCKIEPfI9D32EnsP6oasduSg",
						"authorChannelId": {
							"value": "UCKIEPfI9D32EnsP6oasduSg"
						},
						"canRate": true,
						"viewerRating": "none",
						"likeCount": 2,
						"publishedAt": "2021-10-22T04:56:44Z",
						"updatedAt": "2021-10-22T04:56:44Z"
					}
				},
				{
					"kind": "youtube#comment",
					"etag": "uL4Ihb6CwzyX58qbrohHGtDPwlg",
					"id": "Ugwk0eopK8QTv5oFPIR4AaABAg.9TmMirE421c9TnVQZXYJHv",
					"snippet": {
						"channelId": "UCKIEPfI9D32EnsP6oasduSg",
						"videoId": "7kcz6q83bck",
						"textDisplay": "@@alljit2899 ขอบพระคุณมากๆ คำแนะนำดีต่อใจมากๆค่ะ",
						"textOriginal": "@@alljit2899 ขอบพระคุณมากๆ คำแนะนำดีต่อใจมากๆค่ะ",
						"parentId": "Ugwk0eopK8QTv5oFPIR4AaABAg",
						"authorDisplayName": "@pechcyn.2136",
						"authorProfileImageUrl": "https://yt3.ggpht.com/ytc/AIf8zZSsi0bd7Jdhgr27F5gAQ5911D-plSnr8enWow=s48-c-k-c0x00ffffff-no-rj",
						"authorChannelUrl": "http://www.youtube.com/channel/UCfsKplNElrG6rzC-qrRr2ow",
						"authorChannelId": {
							"value": "UCfsKplNElrG6rzC-qrRr2ow"
						},
						"canRate": true,
						"viewerRating": "none",
						"likeCount": 0,
						"publishedAt": "2021-10-22T10:44:55Z",
						"updatedAt": "2021-10-22T10:44:55Z"
					}
				}
			]
		}
	},
	{
		"kind": "youtube#commentThread",
		"etag": "8LsUi8okCAONVii_OPW9y6Sd3d0",
		"id": "UgymFOD8NyciO-QSCQt4AaABAg",
		"snippet": {
			"channelId": "UCKIEPfI9D32EnsP6oasduSg",
			"videoId": "7kcz6q83bck",
			"topLevelComment": {
				"kind": "youtube#comment",
				"etag": "Xaumf98IQcyiTspPCc4z240CSx4",
				"id": "UgymFOD8NyciO-QSCQt4AaABAg",
				"snippet": {
					"channelId": "UCKIEPfI9D32EnsP6oasduSg",
					"videoId": "7kcz6q83bck",
					"textDisplay": "ถ้าเจอคนเฮงซวย ต้องบวกเท่านั้นครับ!",
					"textOriginal": "ถ้าเจอคนเฮงซวย ต้องบวกเท่านั้นครับ!",
					"authorDisplayName": "@charlemchaiweecharrugson9376",
					"authorProfileImageUrl": "https://yt3.ggpht.com/ytc/AIf8zZR5zE4BVbfWzCp0rIh7MVJdyYsB5rGBTI4rtQ=s48-c-k-c0x00ffffff-no-rj",
					"authorChannelUrl": "http://www.youtube.com/channel/UCjiJVUvkruKQZlIwy91rJRg",
					"authorChannelId": {
						"value": "UCjiJVUvkruKQZlIwy91rJRg"
					},
					"canRate": true,
					"viewerRating": "none",
					"likeCount": 3,
					"publishedAt": "2021-10-20T17:25:09Z",
					"updatedAt": "2021-10-20T17:25:09Z"
				}
			},
			"canReply": true,
			"totalReplyCount": 2,
			"isPublic": true
		},
		"replies": {
			"comments": [
				{
					"kind": "youtube#comment",
					"etag": "t5_RTXY4IFabdKEcQNgpcL7DuYk",
					"id": "UgymFOD8NyciO-QSCQt4AaABAg.9Tj3dBU9q5X9TkFArWjy1m",
					"snippet": {
						"channelId": "UCKIEPfI9D32EnsP6oasduSg",
						"videoId": "7kcz6q83bck",
						"textDisplay": "มีเรื่องอะไรไม่สบายใจมาระบายที่แอป Alljit ได้นะคะ❤",
						"textOriginal": "มีเรื่องอะไรไม่สบายใจมาระบายที่แอป Alljit ได้นะคะ❤",
						"parentId": "UgymFOD8NyciO-QSCQt4AaABAg",
						"authorDisplayName": "@alljit2899",
						"authorProfileImageUrl": "https://yt3.ggpht.com/9G1VHwlixOYAKYITU2BIjS5JAlBCGPp9ynPRsZQcdigQLvSokTuhPb28QTiSf2rPzQHMReIV1yw=s48-c-k-c0x00ffffff-no-rj",
						"authorChannelUrl": "http://www.youtube.com/channel/UCKIEPfI9D32EnsP6oasduSg",
						"authorChannelId": {
							"value": "UCKIEPfI9D32EnsP6oasduSg"
						},
						"canRate": true,
						"viewerRating": "none",
						"likeCount": 0,
						"publishedAt": "2021-10-21T04:25:14Z",
						"updatedAt": "2021-10-21T04:25:14Z"
					}
				},
				{
					"kind": "youtube#comment",
					"etag": "IhjPTiuxben1QrAlWMINWki7fKw",
					"id": "UgymFOD8NyciO-QSCQt4AaABAg.9Tj3dBU9q5X9TpLzmJN-ew",
					"snippet": {
						"channelId": "UCKIEPfI9D32EnsP6oasduSg",
						"videoId": "7kcz6q83bck",
						"textDisplay": "ขอบคุณมากครับป🤣",
						"textOriginal": "ขอบคุณมากครับป🤣",
						"parentId": "UgymFOD8NyciO-QSCQt4AaABAg",
						"authorDisplayName": "@user-bp7gj9tw9r",
						"authorProfileImageUrl": "https://yt3.ggpht.com/ytc/AIf8zZRrGa66V46_1wx-w4KMIuSBZdEpNATgjncly-O_6A=s48-c-k-c0x00ffffff-no-rj",
						"authorChannelUrl": "http://www.youtube.com/channel/UCWCo2aIO3liqrRYTPwbdHYA",
						"authorChannelId": {
							"value": "UCWCo2aIO3liqrRYTPwbdHYA"
						},
						"canRate": true,
						"viewerRating": "none",
						"likeCount": 0,
						"publishedAt": "2021-10-23T04:00:57Z",
						"updatedAt": "2021-10-23T04:00:57Z"
					}
				}
			]
		}
	},
	{
		"kind": "youtube#commentThread",
		"etag": "PLrWitthqyfIFUC3nhEz6IUStVg",
		"id": "Ugy-5lmAQb_G68bcy2x4AaABAg",
		"snippet": {
			"channelId": "UCKIEPfI9D32EnsP6oasduSg",
			"videoId": "7kcz6q83bck",
			"topLevelComment": {
				"kind": "youtube#comment",
				"etag": "a2TKHrVp32fwvdqHhSCvt25xiJQ",
				"id": "Ugy-5lmAQb_G68bcy2x4AaABAg",
				"snippet": {
					"channelId": "UCKIEPfI9D32EnsP6oasduSg",
					"videoId": "7kcz6q83bck",
					"textDisplay": "รัก ออจิ",
					"textOriginal": "รัก ออจิ",
					"authorDisplayName": "@NikeOemError",
					"authorProfileImageUrl": "https://yt3.ggpht.com/lKXjJasYQVac_TOdrcgBegjMDKJG-9oQZKcPgj7K_ruV5RJnjs9x3tFHPikOdR3jCHgVrrf7=s48-c-k-c0x00ffffff-no-rj",
					"authorChannelUrl": "http://www.youtube.com/channel/UCCI-ElHexYXX1FdSbKpwHaA",
					"authorChannelId": {
						"value": "UCCI-ElHexYXX1FdSbKpwHaA"
					},
					"canRate": true,
					"viewerRating": "none",
					"likeCount": 1,
					"publishedAt": "2021-10-20T16:10:41Z",
					"updatedAt": "2021-10-20T16:10:41Z"
				}
			},
			"canReply": true,
			"totalReplyCount": 1,
			"isPublic": true
		},
		"replies": {
			"comments": [
				{
					"kind": "youtube#comment",
					"etag": "iFkOepldmZO1wktfyG7cdKiii70",
					"id": "Ugy-5lmAQb_G68bcy2x4AaABAg.9Tiw6nl-b8f9TkFCLjCCP7",
					"snippet": {
						"channelId": "UCKIEPfI9D32EnsP6oasduSg",
						"videoId": "7kcz6q83bck",
						"textDisplay": "ขอบคุณมากๆนะคะ💕",
						"textOriginal": "ขอบคุณมากๆนะคะ💕",
						"parentId": "Ugy-5lmAQb_G68bcy2x4AaABAg",
						"authorDisplayName": "@alljit2899",
						"authorProfileImageUrl": "https://yt3.ggpht.com/9G1VHwlixOYAKYITU2BIjS5JAlBCGPp9ynPRsZQcdigQLvSokTuhPb28QTiSf2rPzQHMReIV1yw=s48-c-k-c0x00ffffff-no-rj",
						"authorChannelUrl": "http://www.youtube.com/channel/UCKIEPfI9D32EnsP6oasduSg",
						"authorChannelId": {
							"value": "UCKIEPfI9D32EnsP6oasduSg"
						},
						"canRate": true,
						"viewerRating": "none",
						"likeCount": 0,
						"publishedAt": "2021-10-21T04:25:26Z",
						"updatedAt": "2021-10-21T04:25:26Z"
					}
				}
			]
		}
	},
	{
		"kind": "youtube#commentThread",
		"etag": "CDxZC3j6rRQa4X8rbopwxHC7EAI",
		"id": "UgxoWFhm8D5qgZAqAA94AaABAg",
		"snippet": {
			"channelId": "UCKIEPfI9D32EnsP6oasduSg",
			"videoId": "7kcz6q83bck",
			"topLevelComment": {
				"kind": "youtube#comment",
				"etag": "GrGaTS66ytR-IUD4jcm-aNCYoos",
				"id": "UgxoWFhm8D5qgZAqAA94AaABAg",
				"snippet": {
					"channelId": "UCKIEPfI9D32EnsP6oasduSg",
					"videoId": "7kcz6q83bck",
					"textDisplay": "สวัสดีคะ",
					"textOriginal": "สวัสดีคะ",
					"authorDisplayName": "@mylovehabibi3186",
					"authorProfileImageUrl": "https://yt3.ggpht.com/iU19eV7KgjDffWMjF6wgT2kyE-2IAznDHbafqFMUSYaPuX4PZ-MQM89kXmSUzn4w4qUpAkT8Rg=s48-c-k-c0x00ffffff-no-rj",
					"authorChannelUrl": "http://www.youtube.com/channel/UC8U0sxeNingRdFHYszF87zg",
					"authorChannelId": {
						"value": "UC8U0sxeNingRdFHYszF87zg"
					},
					"canRate": true,
					"viewerRating": "none",
					"likeCount": 0,
					"publishedAt": "2021-10-20T09:33:34Z",
					"updatedAt": "2021-10-20T09:33:34Z"
				}
			},
			"canReply": true,
			"totalReplyCount": 1,
			"isPublic": true
		},
		"replies": {
			"comments": [
				{
					"kind": "youtube#comment",
					"etag": "-9ZoS0IaWRjOVlkenv0Vaw6S53I",
					"id": "UgxoWFhm8D5qgZAqAA94AaABAg.9TiDfEarsC09TiMgRtuIp_",
					"snippet": {
						"channelId": "UCKIEPfI9D32EnsP6oasduSg",
						"videoId": "7kcz6q83bck",
						"textDisplay": "สวัสดีค่ะ มีเรื่องอะไรไม่สบายใจมาระบายที่แอป Alljit ได้นะคะ💕",
						"textOriginal": "สวัสดีค่ะ มีเรื่องอะไรไม่สบายใจมาระบายที่แอป Alljit ได้นะคะ💕",
						"parentId": "UgxoWFhm8D5qgZAqAA94AaABAg",
						"authorDisplayName": "@alljit2899",
						"authorProfileImageUrl": "https://yt3.ggpht.com/9G1VHwlixOYAKYITU2BIjS5JAlBCGPp9ynPRsZQcdigQLvSokTuhPb28QTiSf2rPzQHMReIV1yw=s48-c-k-c0x00ffffff-no-rj",
						"authorChannelUrl": "http://www.youtube.com/channel/UCKIEPfI9D32EnsP6oasduSg",
						"authorChannelId": {
							"value": "UCKIEPfI9D32EnsP6oasduSg"
						},
						"canRate": true,
						"viewerRating": "none",
						"likeCount": 1,
						"publishedAt": "2021-10-20T10:52:22Z",
						"updatedAt": "2021-10-20T10:52:22Z"
					}
				}
			]
		}
	}
]